{
  "services": [
    {
      "product": "service-name",
      "component": "frontend",
      "promotionType": "library",
      "checks": [
        {
          "checkTypes": ["unit"],
          "provider": "GitHub",
          "phase": "pre-merge",
          "config": {
            "file": ".github/workflows/tests.yaml",
            "path": "$.jobs.unit"
          }
        },
        {
          "checkTypes": ["code style and linting"],
          "provider": "GitHub",
          "phase": "pre-merge",
          "config": {
            "file": ".github/workflows/quality.yaml",
            "path": "$.jobs.lint.steps[?@.name=='Run linter']"
          }
        },
        {
          "checkTypes": ["unit"],
          "provider": "GitHub",
          "phase": "pre-release",
          "config": {
            "file": ".github/workflows/release.yaml",
            "path": "$.jobs.test"
          }
        }
      ]
    }
  ]
}
